oprounder/__init__.py
oprounder/rounder.py
optimized_rounder-0.1.3.dist-info/LICENSE
optimized_rounder-0.1.3.dist-info/METADATA
optimized_rounder-0.1.3.dist-info/WHEEL
optimized_rounder-0.1.3.dist-info/top_level.txt
optimized_rounder-0.1.3.dist-info/RECORD
