Metadata-Version: 2.2
Name: optimized-rounder
Version: 0.1.3
Summary: An optimizer for finding optimal thresholds in ordinal classification problems
License: MIT
Project-URL: Homepage, https://github.com/susuky/optimized-rounder
Project-URL: Bug Tracker, https://github.com/susuky/optimized-rounder/issues
Keywords: machine learning,optimization,thresholds,ordinal classification
Classifier: Programming Language :: Python :: 3
Classifier: License :: OSI Approved :: MIT License
Classifier: Operating System :: OS Independent
Classifier: Intended Audience :: Science/Research
Classifier: Topic :: Scientific/Engineering :: Artificial Intelligence
Requires-Python: >=3.9
License-File: LICENSE
Requires-Dist: numpy
Requires-Dist: optuna
Requires-Dist: scikit-learn
